sinapsis_kokoro/__init__.py
sinapsis_kokoro/helpers/kokoro_utils.py
sinapsis_kokoro/helpers/tags.py
sinapsis_kokoro/templates/__init__.py
sinapsis_kokoro/templates/kokoro_tts.py
sinapsis_kokoro-0.1.9.dist-info/licenses/LICENSE
sinapsis_kokoro-0.1.9.dist-info/METADATA
sinapsis_kokoro-0.1.9.dist-info/WHEEL
sinapsis_kokoro-0.1.9.dist-info/top_level.txt
sinapsis_kokoro-0.1.9.dist-info/RECORD
