Metadata-Version: 2.4
Name: sinapsis-kokoro
Version: 0.1.9
Summary: Text to speech using Kokoro TTS model
Author-email: SinapsisAI <dev@sinapsis.tech>
Project-URL: Homepage, https://sinapsis.tech
Project-URL: Documentation, https://docs.sinapsis.tech/docs
Project-URL: Tutorials, https://docs.sinapsis.tech/tutorials
Project-URL: Repository, https://github.com/Sinapsis-AI/sinapsis-speech.git
Requires-Python: >=3.10
License-File: LICENSE
Requires-Dist: kokoro>=0.9.4
Requires-Dist: pip>=25.0.1
Requires-Dist: sinapsis>=0.2.3
Provides-Extra: data-tools
Requires-Dist: sinapsis-data-readers>=0.1.2; extra == "data-tools"
Requires-Dist: sinapsis-data-writers[soundfile]>=0.1.2; extra == "data-tools"
Provides-Extra: all
Requires-Dist: sinapsis-kokoro[data-tools]; extra == "all"
Provides-Extra: kokoro-app
Requires-Dist: sinapsis[webapp]>=0.2.3; extra == "kokoro-app"
Dynamic: license-file
